chibi_dl_tmo/__init__.py
chibi_dl_tmo/chibi_dl_tmo.py
chibi_dl_tmo/cli.py
chibi_dl_tmo/episode.py
chibi_dl_tmo/exceptions.py
chibi_dl_tmo/regex.py
chibi_dl_tmo/serie.py
chibi_dl_tmo/site.py
chibi_dl_tmo-1.1.0.dist-info/AUTHORS.rst
chibi_dl_tmo-1.1.0.dist-info/LICENSE
chibi_dl_tmo-1.1.0.dist-info/METADATA
chibi_dl_tmo-1.1.0.dist-info/WHEEL
chibi_dl_tmo-1.1.0.dist-info/entry_points.txt
chibi_dl_tmo-1.1.0.dist-info/top_level.txt
chibi_dl_tmo-1.1.0.dist-info/RECORD
