Metadata-Version: 2.1
Name: chibi_dl_tmo
Version: 1.1.0
Summary: command script for download mangas from lectortmo.com or visortmo.com
Home-page: https://github.com/dem4ply/chibi_dl_tmo
Author: dem4ply
Author-email: dem4ply@gmail.com
License: WTFPL
Keywords: chibi_dl_tmo
Classifier: Development Status :: 2 - Pre-Alpha
Classifier: Intended Audience :: Developers
Classifier: License :: Public Domain
Classifier: Natural Language :: English
Classifier: Programming Language :: Python :: 3.7
Classifier: Programming Language :: Python :: 3.8
License-File: LICENSE
License-File: AUTHORS.rst
Requires-Dist: chibi-dl >=0.1.2
Requires-Dist: undetected-chromedriver >=3.5.2
